{
  "creds": {
    "noiseKey": {
      "private": {
        "type": "Buffer",
        "data": "iMJKyE6SARI+hz6RbJUJdaPRbmSU5EPE2nFI++zQJ1U="
      },
      "public": {
        "type": "Buffer",
        "data": "VMBQTp5KE4Pa6vRp6K1a+2TWdqbv67oN9XtDo59pfAo="
      }
    },
    "signedIdentityKey": {
      "private": {
        "type": "Buffer",
        "data": "KKt5PU24e6n4W849RVntemGcbdnrw2qmpp1nzTnfsVw="
      },
      "public": {
        "type": "Buffer",
        "data": "b3ex+MrvKAXxclh3tHz0S89fGMUoTskl7yEWZE81bG4="
      }
    },
    "signedPreKey": {
      "keyPair": {
        "private": {
          "type": "Buffer",
          "data": "YKFvzWZiEaTlyrcoVswka6umA4/EogMHW0phLGKf/0M="
        },
        "public": {
          "type": "Buffer",
          "data": "9BRaPdOnaPazm1nx9+XzZu3Gtk1nzw3IDoXkbQyu910="
        }
      },
      "signature": {
        "type": "Buffer",
        "data": "GBXfdp8tYkuOm2GpX4/yyE7luh2taGW00KhfCfuXydPfMAYt0KnsmupmNKwSAhpsuFxC6dY7ykMukF/ANTfrBg=="
      },
      "keyId": 1
    },
    "registrationId": 18,
    "advSecretKey": "xpckKOljzMz+REK2qNcLoYqIL8F3Sj+qufuURJY0FZ0=",
    "processedHistoryMessages": [
      {
        "key": {
          "remoteJid": "6285759681568@s.whatsapp.net",
          "fromMe": true,
          "id": "A0C989F210CE280B6457EA046BAD80BB"
        },
        "messageTimestamp": 1662645121
      },
      {
        "key": {
          "remoteJid": "6285759681568@s.whatsapp.net",
          "fromMe": true,
          "id": "2E92FB0DD2B721655F42C573501D6EE5"
        },
        "messageTimestamp": 1662645123
      }
    ],
    "nextPreKeyId": 31,
    "firstUnuploadedPreKeyId": 31,
    "accountSettings": {
      "unarchiveChats": false
    },
    "account": {
      "details": "CKz50voGENfm55gGGAE=",
      "accountSignatureKey": "f6pksaHi9hLb8y2CwyoubzfE37sM56ylQ4lvY68SZV4=",
      "accountSignature": "J3yBRPeThA7KdbJSui/cnxXrkB0taaDjgwrskZpci51HvCKpRRWSM0yR4UvQFFW2yHa4/AVn9MmmFsvoRVnGBg==",
      "deviceSignature": "AVdwzxKAXBO2yOKePb8E/BAM0zNnaIUwJWmeo6kCXRx5Wc/q+ZGQxEXaoMkJcLoIurqEzW4w2ctkI49cXHt2BA=="
    },
    "me": {
      "id": "6285759681568:29@s.whatsapp.net",
      "name": "XzzyoBOT",
      "jid": "6285759681568@s.whatsapp.net"
    },
    "signalIdentities": [
      {
        "identifier": {
          "name": "6285759681568:29@s.whatsapp.net",
          "deviceId": 0
        },
        "identifierKey": {
          "type": "Buffer",
          "data": "BX+qZLGh4vYS2/MtgsMqLm83xN+7DOespUOJb2OvEmVe"
        }
      }
    ],
    "platform": "smba",
    "lastAccountSyncTimestamp": 1662645101,
    "myAppStateKeyId": "AAAAAEWD"
  },
  "keys": {
    "preKeys": {
      "1": {
        "private": {
          "type": "Buffer",
          "data": "YHlkb9RR+HbrxkjEvnmLnVcZ4dEZsGPSoaQf6NvkRUE="
        },
        "public": {
          "type": "Buffer",
          "data": "re8eBrk7SyKcsEG4yv5Bpc0CaYLsX2CJsml4A20eQFo="
        }
      },
      "2": {
        "private": {
          "type": "Buffer",
          "data": "qLmpd1rJ8j8TuGOpx7WtWRf3OM9CBFXjZDKZCWDmd1Y="
        },
        "public": {
          "type": "Buffer",
          "data": "6DDM1/U85srKcSC80U8LhkPbEHfZA6CkZT9JOxruBRM="
        }
      },
      "3": null,
      "4": null,
      "5": {
        "private": {
          "type": "Buffer",
          "data": "EKZL90Oj+EPqTbdFIICWKSBxBJLp+1tphSCaeCwVi3Q="
        },
        "public": {
          "type": "Buffer",
          "data": "J7SxD6jQtkA1xqZexEvFQy07ywSg0Z/l6/Xt9qyTawk="
        }
      },
      "6": {
        "private": {
          "type": "Buffer",
          "data": "0M+9pg0VKkkw9ln5jaKOey4HLDSt0o/h+kNZBRFyu3A="
        },
        "public": {
          "type": "Buffer",
          "data": "BMu8IRXMcIcPaIzwFuPqST664glI/W3Q82aIre7ckFY="
        }
      },
      "7": {
        "private": {
          "type": "Buffer",
          "data": "EOkEtFsOK3JiHBo7x2X3jShg6MXwwCikI9OQEIU6DFw="
        },
        "public": {
          "type": "Buffer",
          "data": "8pRmcWhI3W1Cc+Q2n3lbfSlxAIlfkhXqRQqoQtjVvUE="
        }
      },
      "8": {
        "private": {
          "type": "Buffer",
          "data": "kDLj0wvPL7k7Jj0mQqIMqqmVHdlhY+818GRyol1nTVE="
        },
        "public": {
          "type": "Buffer",
          "data": "ZVLbd0pN/M4h4v3luJGHcw8WDRHsKEpB0x/NJSShaBE="
        }
      },
      "9": {
        "private": {
          "type": "Buffer",
          "data": "WLYReXnWFnGS54dxiUsePSx+7go7oljlIdTJ+iLD7nI="
        },
        "public": {
          "type": "Buffer",
          "data": "wlw4wvTJbzJacqysDTUI8N7NEoKFCv5QC9B6DAuv9jA="
        }
      },
      "10": null,
      "11": {
        "private": {
          "type": "Buffer",
          "data": "gDpgMkZUvLVWzuxGj90UeU+wrAb5L0eXXcz7Raofg2w="
        },
        "public": {
          "type": "Buffer",
          "data": "Gej/sA+GmFwObTUrlLhN8ML6VfvaGALo3kn96hJq/3o="
        }
      },
      "12": {
        "private": {
          "type": "Buffer",
          "data": "YOQJ36YLtK7PNeZTXBFSlDpMRkZsUKeL/TgeDMDSbGc="
        },
        "public": {
          "type": "Buffer",
          "data": "9VU71wfzBp80yscec3n6dJEJ/uxJzfLIxLqL+TiW2kM="
        }
      },
      "13": {
        "private": {
          "type": "Buffer",
          "data": "CKyqHBh7Z8aAnPVzbMqYh4E4qfQbiVDZxU6xat/z4EM="
        },
        "public": {
          "type": "Buffer",
          "data": "4cnK2f0X3MYEMC5Q3OFjVe0f8t19FDeYLxluGC4gFFE="
        }
      },
      "14": null,
      "15": {
        "private": {
          "type": "Buffer",
          "data": "aIkwSpCvEtbz5M6yDoYpQ3LpoUx7Kw04Kft4cbH63V4="
        },
        "public": {
          "type": "Buffer",
          "data": "eaxlOd7po4U/mUMTZY1v21c4IoeNKwbaczIYclcMH38="
        }
      },
      "16": null,
      "17": {
        "private": {
          "type": "Buffer",
          "data": "CPtnPNjQHSs6iTv5Ax0mgmWnYckTDVOD3/xnu8SiPF0="
        },
        "public": {
          "type": "Buffer",
          "data": "JAotQ6ZRvA6lyvqkZ7p/mSJdyrjp/61vrdNoNafkuyQ="
        }
      },
      "18": {
        "private": {
          "type": "Buffer",
          "data": "EJyjBChD4ZSKpOXix0MMBVpHighAhu/Ww/TqJeF3jGs="
        },
        "public": {
          "type": "Buffer",
          "data": "CGBY1pAeysFzwjytwktLNWYL5yqfwKwQyldd6jIszkQ="
        }
      },
      "19": {
        "private": {
          "type": "Buffer",
          "data": "mFsSfZfFnMZhw1MTJKND3T4rG4CfdV5frmm7td5cTkw="
        },
        "public": {
          "type": "Buffer",
          "data": "MS7iE/IwaoW1dTWY0o5/OwnRtltb85ReJXRvGtM0Pxs="
        }
      },
      "20": {
        "private": {
          "type": "Buffer",
          "data": "KE5WVBtJuUJ3hCnVv4RR+nNo8NU12bPKtZFFpXQl9F4="
        },
        "public": {
          "type": "Buffer",
          "data": "bPwD+yK+sQfta9YGz2Rukn7KWq6KFY9cNDM1Kb5DQno="
        }
      },
      "21": {
        "private": {
          "type": "Buffer",
          "data": "gLWu8nYvJd9fZPRUgOQfD1eonyfgb4EqSAkGAhE/nlk="
        },
        "public": {
          "type": "Buffer",
          "data": "31+1fedT/t/T6mwHIVdyDwYB2YdReeZRvhX7/qEaojk="
        }
      },
      "22": {
        "private": {
          "type": "Buffer",
          "data": "COsDKaH0Vy0x32PoWYYOh4Iy3f9JRsEiGjqqpbZQWGI="
        },
        "public": {
          "type": "Buffer",
          "data": "GhFPQe0zNGahTWiO8FwLsCLwvgNdEVeQ7dhW3nfjvWs="
        }
      },
      "23": {
        "private": {
          "type": "Buffer",
          "data": "8IxeIWwC5KcKZQbYlU3okGN3rGtr2+4BGu3GdFYRflY="
        },
        "public": {
          "type": "Buffer",
          "data": "CjDc0NytP6x/xJGi5eWZ/6L8WmgIpRtM5nUzXQgf5x0="
        }
      },
      "24": {
        "private": {
          "type": "Buffer",
          "data": "0GfFFR0Ej9t24mDgOIPauG9UMHjlT2/63PQyYJnCnHc="
        },
        "public": {
          "type": "Buffer",
          "data": "dIWZ7+YEGKXjJkaQNmBPa/3M4XfQ5EJItaKO3s7IiUQ="
        }
      },
      "25": {
        "private": {
          "type": "Buffer",
          "data": "MMQbZOCG4C3bDmoWh5YU5BMHAph9Ebhk/i/PiZG1qkM="
        },
        "public": {
          "type": "Buffer",
          "data": "iLwtAoYm5aj3dKR9Hg1CgzT7ajpYj9pzYd6N0Nk063w="
        }
      },
      "26": null,
      "27": {
        "private": {
          "type": "Buffer",
          "data": "EBMvrQnaijcmIIfixuywBh6t9WLnrt+ZEnbF5ag+tFg="
        },
        "public": {
          "type": "Buffer",
          "data": "MoifOxr7eL9cvpeYBDTjy8tF53BUfV9yF8qMUzzWXTI="
        }
      },
      "28": null,
      "29": {
        "private": {
          "type": "Buffer",
          "data": "UFFXPjGbH1U2iRLncdxNJfjblzgQCK49AxNPLZxenHo="
        },
        "public": {
          "type": "Buffer",
          "data": "Wddn8TPwXWHAwSP/zC0xyB44u3YLJ+KjvDH2qsUsOmo="
        }
      },
      "30": {
        "private": {
          "type": "Buffer",
          "data": "sEjCfMYrdvDd8Yqc4YC4+ixC6oEQ0RhQkpqmU3eIaWs="
        },
        "public": {
          "type": "Buffer",
          "data": "KgPFjOpUDSYh7d6+sevuP1zT3s3Z6EMWQzjl5279Vmo="
        }
      }
    },
    "sessions": {
      "62895622167663.0": {
        "_sessions": {
          "BbMJR/I/FKvcNaaZu1E50PNLxX6KZ+bXd/dK/xBWLmR7": {
            "registrationId": 1727665749,
            "currentRatchet": {
              "ephemeralKeyPair": {
                "pubKey": "BSx5kM8Y0wLhwmQUZ4s4AF0DkPPmdyxA8rundimHxgR4",
                "privKey": "wIW0GnH36klP2BN1QGG5jfRflCA9oq1lM9K95sQgtmM="
              },
              "lastRemoteEphemeralKey": "Bbfqo1fVTHi766hDw9gwTTonRsVNhVA0PTBdhH2rEIQb",
              "previousCounter": 0,
              "rootKey": "FTrfSREuqIDMcs8PJYqsOWhILMQZy5sNe1pI8t35uY8="
            },
            "indexInfo": {
              "baseKey": "BbMJR/I/FKvcNaaZu1E50PNLxX6KZ+bXd/dK/xBWLmR7",
              "baseKeyType": 2,
              "closed": -1,
              "used": 1662645105006,
              "created": 1662645105006,
              "remoteIdentityKey": "BVJ2Zz3i7DME+4LuXeY78Y0Am3XfkyoK/EGsSSqLxTVx"
            },
            "_chains": {
              "Bbfqo1fVTHi766hDw9gwTTonRsVNhVA0PTBdhH2rEIQb": {
                "chainKey": {
                  "counter": 0,
                  "key": "2caF20RyOudgzYvVHoI4eblx+jrVV35CxGUkaPboIrc="
                },
                "chainType": 2,
                "messageKeys": {}
              },
              "BSx5kM8Y0wLhwmQUZ4s4AF0DkPPmdyxA8rundimHxgR4": {
                "chainKey": {
                  "counter": -1,
                  "key": "1+v99Eg/A2JaLmDXwzeOZCzlOoRffQ2bHpESZcU9ZAU="
                },
                "chainType": 1,
                "messageKeys": {}
              }
            }
          }
        },
        "version": "v1"
      },
      "6289602101027.0": {
        "_sessions": {
          "BUuUb0EXzA0IoOT3VJO6OW4I7Uao1uyCPaIqiC1wVmRp": {
            "registrationId": 2025908687,
            "currentRatchet": {
              "ephemeralKeyPair": {
                "pubKey": "BY/MRGWnOU3drJmSxbRVQScJRji6iytQ65JMJTdb1CEu",
                "privKey": "qJAnX7qeCZXLU/GPVgWH0L23Xg6LCmTm3PfQyshqNGI="
              },
              "lastRemoteEphemeralKey": "BUKzrwHaRujF6ODzEdTU07z7dI1iHDCOFRdO4eeRTYVU",
              "previousCounter": 0,
              "rootKey": "YIZxHVNI2i9zxKPnpMLaMnC7mtV08u35NrC9kKLgUqQ="
            },
            "indexInfo": {
              "baseKey": "BUuUb0EXzA0IoOT3VJO6OW4I7Uao1uyCPaIqiC1wVmRp",
              "baseKeyType": 2,
              "closed": -1,
              "used": 1662645110993,
              "created": 1662645110993,
              "remoteIdentityKey": "BSCJQ0m/15NefOkoltRijqyhrAiy7N2vcO1xr7O/Q1sR"
            },
            "_chains": {
              "BUKzrwHaRujF6ODzEdTU07z7dI1iHDCOFRdO4eeRTYVU": {
                "chainKey": {
                  "counter": 0,
                  "key": "MlSiauFgo70KnOldC2fvB0rvGpn/v5YEQqW1XmrMn9Q="
                },
                "chainType": 2,
                "messageKeys": {}
              },
              "BY/MRGWnOU3drJmSxbRVQScJRji6iytQ65JMJTdb1CEu": {
                "chainKey": {
                  "counter": -1,
                  "key": "dKwTWtq9EW5n7WK4sEHjSHz5nucLJKdxFCYXVthda38="
                },
                "chainType": 1,
                "messageKeys": {}
              }
            }
          }
        },
        "version": "v1"
      },
      "6287861470996.0": {
        "_sessions": {
          "Bc5gzi5i8EiUdK7WzpEutRE0D2VVlcVlJrZABR+FWH1B": {
            "registrationId": 854481982,
            "currentRatchet": {
              "ephemeralKeyPair": {
                "pubKey": "BcjrLjHiJu6aSU148Cu5nG//20cM9p6OoKW3miFTtNlz",
                "privKey": "mIOKoWItzlGeDGVsHrAkCamPzJc5QCUt1UWSdu4DRF8="
              },
              "lastRemoteEphemeralKey": "BcfNPdvMjlRLxtAYkAYp8tvAPAEt6joJkQEw5FL58Ak4",
              "previousCounter": 0,
              "rootKey": "lxBeLuChw0R627SaIU5pMfhkidlYxNY963qMrcWxij0="
            },
            "indexInfo": {
              "baseKey": "Bc5gzi5i8EiUdK7WzpEutRE0D2VVlcVlJrZABR+FWH1B",
              "baseKeyType": 2,
              "closed": -1,
              "used": 1662645111131,
              "created": 1662645111131,
              "remoteIdentityKey": "BZtCDdaw7lvfVzXzMONKCS1JqcDhTsSWvh+hDV2AIo9d"
            },
            "_chains": {
              "BcfNPdvMjlRLxtAYkAYp8tvAPAEt6joJkQEw5FL58Ak4": {
                "chainKey": {
                  "counter": 0,
                  "key": "EJscbSXbJasvxsVB8Fn0nys1QV1iRxmXk8+a7gnULpY="
                },
                "chainType": 2,
                "messageKeys": {}
              },
              "BcjrLjHiJu6aSU148Cu5nG//20cM9p6OoKW3miFTtNlz": {
                "chainKey": {
                  "counter": -1,
                  "key": "pnT+zCVkcm+ulsZ+B7jcc1vn2GMqdC9+iBujRvfh0U0="
                },
                "chainType": 1,
                "messageKeys": {}
              }
            }
          }
        },
        "version": "v1"
      },
      "6287750557390.0": {
        "_sessions": {
          "BRZIxYTm13WllJzCUSU6h3htFuRVzAOysb6XGwV/K1pA": {
            "registrationId": 748757582,
            "currentRatchet": {
              "ephemeralKeyPair": {
                "pubKey": "BTG+RhB7B79Hg1jwWD0iJbHnCqN2tB2OM9duDBW460ol",
                "privKey": "wAfRPohUR8Gl1ZDIPnZsF0sLzfPZR82v+gM1hpW49WQ="
              },
              "lastRemoteEphemeralKey": "BfljAA1Kr635yglDri1tlwbVoZnAsGaXlokyXphiUj1E",
              "previousCounter": 0,
              "rootKey": "qbeV1aYkOfxM/LFzPOZ5ehclZmFTYVkpOSJIVnrrRII="
            },
            "indexInfo": {
              "baseKey": "BRZIxYTm13WllJzCUSU6h3htFuRVzAOysb6XGwV/K1pA",
              "baseKeyType": 2,
              "closed": -1,
              "used": 1662645112139,
              "created": 1662645112139,
              "remoteIdentityKey": "BWfR/SdiLVfaRtc4PiBetY1YATEjJm26wzinM/A4AG5x"
            },
            "_chains": {
              "BfljAA1Kr635yglDri1tlwbVoZnAsGaXlokyXphiUj1E": {
                "chainKey": {
                  "counter": 0,
                  "key": "yMgxPjToN7KInSGm024gXTFWZr4AR3O/RBHqOeZN64g="
                },
                "chainType": 2,
                "messageKeys": {}
              },
              "BTG+RhB7B79Hg1jwWD0iJbHnCqN2tB2OM9duDBW460ol": {
                "chainKey": {
                  "counter": -1,
                  "key": "0+TpprzIdk7shzITRrEciaket3/Z8/SJQgNS7M976ro="
                },
                "chainType": 1,
                "messageKeys": {}
              }
            }
          }
        },
        "version": "v1"
      },
      "6285759681568.0": {
        "_sessions": {
          "BTWyfKeBiHdEeM9813D1N/AYXqQXUVY6jMsDoou/M54+": {
            "registrationId": 1187468887,
            "currentRatchet": {
              "ephemeralKeyPair": {
                "pubKey": "Bd2lYqneUtDB7XglFGa9OPMRtlyNDHuJyysxwycjv+Ig",
                "privKey": "aPAINjOgOp1YqQV4H4GMAV2DPY4shrQXGmb9HVu3yFQ="
              },
              "lastRemoteEphemeralKey": "BUD9u1rtuvM5Rt6OmEQ6cN6Xu+MjXQhcdzeFTIuyHfRa",
              "previousCounter": 0,
              "rootKey": "jF7sGr58eJH3Xec3nyzm/o28HUGPz8Y2n1cMKDlbYVc="
            },
            "indexInfo": {
              "baseKey": "BTWyfKeBiHdEeM9813D1N/AYXqQXUVY6jMsDoou/M54+",
              "baseKeyType": 2,
              "closed": -1,
              "used": 1662645112423,
              "created": 1662645112423,
              "remoteIdentityKey": "BX+qZLGh4vYS2/MtgsMqLm83xN+7DOespUOJb2OvEmVe"
            },
            "_chains": {
              "BUD9u1rtuvM5Rt6OmEQ6cN6Xu+MjXQhcdzeFTIuyHfRa": {
                "chainKey": {
                  "counter": 5,
                  "key": "8LwrbbJ6vNM3HAUbU5bpXUgFEtbVczo7AOYmIcYiYf8="
                },
                "chainType": 2,
                "messageKeys": {}
              },
              "Bd2lYqneUtDB7XglFGa9OPMRtlyNDHuJyysxwycjv+Ig": {
                "chainKey": {
                  "counter": -1,
                  "key": "QC7CDp+GiuhO+aYrmF/iLCv4G1DtOYEUvr0tosjf5Yc="
                },
                "chainType": 1,
                "messageKeys": {}
              }
            }
          }
        },
        "version": "v1"
      },
      "62881022772463.0": {
        "_sessions": {
          "Bbaa1oQk33VHeGu8RBfGgb9U7TOOWVuijs4uhhqmd6MG": {
            "registrationId": 199413666,
            "currentRatchet": {
              "ephemeralKeyPair": {
                "pubKey": "BfDae/ysSH1dhF0VSHMdFPFG2ljLK5D9YFWrSQSDWi1Z",
                "privKey": "AOxkIiBrUAo6A57R/Y1jsHZ+a8ZvebU4vZGuOzE/qGc="
              },
              "lastRemoteEphemeralKey": "BVCgBUl2ktEm2XrmlJw7itxgLr3PVlyqleIiI5mJ7SBH",
              "previousCounter": 0,
              "rootKey": "HnD00kxcc6z0DkcdPHkmYz4gboztqDW43QQqpbIAQ2k="
            },
            "indexInfo": {
              "baseKey": "Bbaa1oQk33VHeGu8RBfGgb9U7TOOWVuijs4uhhqmd6MG",
              "baseKeyType": 2,
              "closed": -1,
              "used": 1662645114503,
              "created": 1662645114503,
              "remoteIdentityKey": "BTFlRFkFGC4c+fRq3NBTpHHKRyka9x4PWSkuiYdiQ3Ej"
            },
            "_chains": {
              "BVCgBUl2ktEm2XrmlJw7itxgLr3PVlyqleIiI5mJ7SBH": {
                "chainKey": {
                  "counter": 0,
                  "key": "vdDnCC9ur+2sSkkrSgLJhYUc05pbzMEzYLfMmo8vM+Y="
                },
                "chainType": 2,
                "messageKeys": {}
              },
              "BfDae/ysSH1dhF0VSHMdFPFG2ljLK5D9YFWrSQSDWi1Z": {
                "chainKey": {
                  "counter": -1,
                  "key": "pb5WOLbTJArXq/+y/Ury/TxQLQBhhXPin8v5X8IyYQk="
                },
                "chainType": 1,
                "messageKeys": {}
              }
            }
          }
        },
        "version": "v1"
      },
      "6285817168673.0": {
        "_sessions": {
          "Ba1OfIY2I2SMbr1tFUjjuyoX3in7wTuf3QSM2g656jQr": {
            "registrationId": 1950430780,
            "currentRatchet": {
              "ephemeralKeyPair": {
                "pubKey": "BUvzkFAVnfOq5GOsKqofV8DNRb+N2nl2F/wRQgwul6RO",
                "privKey": "6Aj9GY06erq1E3gYmFU+vWCkDBZzNcB8wnn99I5tuVk="
              },
              "lastRemoteEphemeralKey": "BVFRS4YtxGwhZlTYNyLC8rBQK93lQnvU38X59HHgCU1Y",
              "previousCounter": 0,
              "rootKey": "Nc3+1TZeZJRKy9QgmNn9l8Dxk8fK5WcoPmgVwJFJ2a0="
            },
            "indexInfo": {
              "baseKey": "Ba1OfIY2I2SMbr1tFUjjuyoX3in7wTuf3QSM2g656jQr",
              "baseKeyType": 2,
              "closed": -1,
              "used": 1662645125451,
              "created": 1662645125451,
              "remoteIdentityKey": "BfqFDXcwRkvJVX+V/h1j727Haja+MmdeKZIilf50PqBt"
            },
            "_chains": {
              "BVFRS4YtxGwhZlTYNyLC8rBQK93lQnvU38X59HHgCU1Y": {
                "chainKey": {
                  "counter": 0,
                  "key": "Ku5nJadFx22+EAmgMwaz8CLPdrgR8poCuimZO1PpHac="
                },
                "chainType": 2,
                "messageKeys": {}
              },
              "BUvzkFAVnfOq5GOsKqofV8DNRb+N2nl2F/wRQgwul6RO": {
                "chainKey": {
                  "counter": -1,
                  "key": "SXto7tuj3G55lwdhizIl38UOzUiQ9eWKJHf5lsx+6RY="
                },
                "chainType": 1,
                "messageKeys": {}
              }
            }
          }
        },
        "version": "v1"
      }
    },
    "senderKeys": {
      "120363024326900769@g.us::62895622167663::0": [
        {
          "senderKeyId": 1597503875,
          "senderChainKey": {
            "iteration": 5,
            "seed": "aivEf7GwEmOAbNRwQu9yaILiT9ik6OlBoVZa6LPgBV8="
          },
          "senderSigningKey": {
            "public": "BYwBTCW7uKp4eq9ls9rD832Wu/YbVSQIDbVAOXGWDLxo"
          }
        }
      ],
      "120363040401575948@g.us::6289602101027::0": [
        {
          "senderKeyId": 1288644783,
          "senderChainKey": {
            "iteration": 13,
            "seed": "E005Sp814Nfh6fn+SBZPlujal0+KHwJPalr+38E3wic="
          },
          "senderSigningKey": {
            "public": "BZmGRZZNxQ0usZN0lDFcCKqqNxUZjFnisXyezHHG9AFs"
          }
        }
      ],
      "status@broadcast::6287861470996::0": [
        {
          "senderKeyId": 2009265969,
          "senderChainKey": {
            "iteration": 3,
            "seed": "7VRYll93LbnzBx+x0XRwyYc4gvF7LutVV4z3+aimch8="
          },
          "senderSigningKey": {
            "public": "BTK2nKEyFli2yE2134Izm/XnnLNISxrzhgJWsv/ULiJt"
          }
        }
      ],
      "120363043417194408@g.us::6287750557390::0": [
        {
          "senderKeyId": 819253146,
          "senderChainKey": {
            "iteration": 7,
            "seed": "9asMOqdH8R2xTtOs58y1PfYyfkBUWWtvfpaKL17SbV8="
          },
          "senderSigningKey": {
            "public": "BczSBISwQPAIOTGM+2qRpkY3evVltDYtdllvzoUrXV0i"
          }
        }
      ],
      "status@broadcast::62881022772463::0": [
        {
          "senderKeyId": 1212219738,
          "senderChainKey": {
            "iteration": 72,
            "seed": "ydBC8fFa5iv5wJzEMkoKPzxnw/eEAJIDJm7nhgJfTEU="
          },
          "senderSigningKey": {
            "public": "BZQsTmdiQY8sV8kfpmlBK70F/2HehnnGas/n8lITlsAx"
          }
        }
      ],
      "120363043417194408@g.us::6285817168673::0": [
        {
          "senderKeyId": 1547383451,
          "senderChainKey": {
            "iteration": 19,
            "seed": "/dDetcv9QEAYA219rgT7tSqcGuCrfiyXuKTZZ9ZIFOQ="
          },
          "senderSigningKey": {
            "public": "BSi3nKP1ILT5jJL51jJO15fopSZrh4zjfx6ki20OO8hb"
          }
        }
      ]
    },
    "appStateSyncKeys": {
      "AAAAAEWD": {
        "keyData": "w1i14Cgrb28PJC4buFZrIknwlMCwpu6GKEFhTjDqXJ0=",
        "fingerprint": {
          "rawId": 1867824300,
          "currentIndex": 1,
          "deviceIndexes": [
            0,
            1
          ]
        },
        "timestamp": "1662645116394"
      }
    },
    "appStateVersions": {
      "critical_block": {
        "version": 1,
        "hash": {
          "type": "Buffer",
          "data": "Owmz+ZlWkHXJDWzpZ8dHh1iL/o2TdJnOAmih3alR5b3wevr5B82jFhbfFPJFPvjzNLq/L3va1Oj8DQV/Z72MVZfHldVjaUXO9sOHsq2w3wPtg8oAtMBDF6AoYRcsv4QKP4YrtJ+b6dJkkn1mQHEdefPVypdlmq7S7SUcHobIyrs="
        },
        "indexValueMap": {
          "mw1x8JP7ZJxKqp+7b7daO+Hz24Xr3K/63sh6r8qjIs4=": {
            "valueMac": {
              "type": "Buffer",
              "data": "x9hbXMATaPb+lfVBzCSSVpgX88cdo4On/5M7DaMrmLo="
            }
          },
          "ohfjs6qtlOx8671IyznhaZmKkRSVY8NkAbCVnzMNW9U=": {
            "valueMac": {
              "type": "Buffer",
              "data": "7VdpiZYy2NfMEl9Qk/MhSxSWk9h09Mj3ioEvw44RYQU="
            }
          }
        }
      },
      "critical_unblock_low": {
        "version": 1,
        "hash": {
          "type": "Buffer",
          "data": "1pwbjRl2Smi75x+2rXywhztX5pw/uQQ8HbEQhuZQdR+CKV2051b0Y3c+Rjk9Y9o8L1/WE8u7Zooz1d7UpwCzzaHgC+kSh1jY4eDZZap+6jh+G1EwMDvDLikijsyv+AVfU6cy2vbivOUhW+q61GKXGqJyyQc4eIgM/0mgkPLu9/o="
        },
        "indexValueMap": {
          "nTwZLIEjYsbkfeW7C2obFqGMR2Sk3Kv69Bfvv+TAG5o=": {
            "valueMac": {
              "type": "Buffer",
              "data": "d9zucXBPWI6Wxo1cInW6+uPvruoTzR221dT5h1FuubA="
            }
          },
          "GfcZfxy5ByRd4Xd2L4NEphu0yxqRM8TWQaOHplHx5eE=": {
            "valueMac": {
              "type": "Buffer",
              "data": "GBV1ZW4NFFJ91R4RrUPjF0aVi1vTaKPEqmzhV71xbIM="
            }
          },
          "Sy612HgYIXwpFx/rydanlJ8h7DD88VOOarvEq+hcscI=": {
            "valueMac": {
              "type": "Buffer",
              "data": "U8QvDYK2/cdFXeXZBq0+LL51wTjLtCd2p1eVJX1gtF4="
            }
          },
          "ix7Xec63qasadW0/To1GAAUZJnZ+zCfL2/xl9uHwltc=": {
            "valueMac": {
              "type": "Buffer",
              "data": "oJ2rJ599l3rwDqeTWUHGOHyigtYaco4cYYSKpLliIEc="
            }
          },
          "YoHAjUMzShbw5IE75pm0Ia8N9XHa6aixoaM0IOMPZXc=": {
            "valueMac": {
              "type": "Buffer",
              "data": "13GGq85abDYjmouDp0bTPa/heXoxoN/kGwTZ3+2ljdY="
            }
          },
          "w3i5ahMeMQ6NdHjBlB1/i3t+05HjupGg4Pkc4/BFS/w=": {
            "valueMac": {
              "type": "Buffer",
              "data": "4kEHXXxj1nS7x4xiGbDKvcgH8TExotXP97KTvip/VOc="
            }
          },
          "IWP9KC/sKEdQe3H3KAc+2HrfuL4n57xDmdbcoUJvFSA=": {
            "valueMac": {
              "type": "Buffer",
              "data": "7MDXbLdzeAfb8GZOEOsQ19Pl0NyBt3VgcA6ixCDVk7o="
            }
          },
          "Dt4oMY97JGagfsgwHAIwUKaEfhevvqEj7fXZZiCNJvs=": {
            "valueMac": {
              "type": "Buffer",
              "data": "yrTiU//UIZaqkzYGCH8TPj4h8SytjnHFVDp4j4GpIYs="
            }
          },
          "LgXmuOlQbC+h5zpBMRGJsS0c+xqddxtfocsIgbbdj/8=": {
            "valueMac": {
              "type": "Buffer",
              "data": "pRIBvs+4jXRNASctKHXb7Uss+6egMrMHzW5n9a60pDw="
            }
          },
          "6+sKBgkAxjMNYpM0TM2MO5O6EO1SfD99jXcFvzUSQG0=": {
            "valueMac": {
              "type": "Buffer",
              "data": "K+c4Ci4wVH8L7BJ7RLfanJ+aY56GA4Fie3cc3CIwxwc="
            }
          },
          "T1fxFKLgX0pOGYPW7dAU/7s0tnE+o+Hpf9J+IoeAtsI=": {
            "valueMac": {
              "type": "Buffer",
              "data": "iCEk2H7TUaTqz21VHffTzcPmd6tluItKYcrvGr239U4="
            }
          },
          "ND8pcO5jvNwLJ/RtgUFgUdGqvdrrRu/rLHVa5p0X+4w=": {
            "valueMac": {
              "type": "Buffer",
              "data": "t5HshcnLPupgvGpW/TDjvw8dpLcBDBRflnprk2RoeVw="
            }
          },
          "6sy2NaLNFx5/I3Q1fiIi5G0i3xwOoYHqlf7Th8+m3Do=": {
            "valueMac": {
              "type": "Buffer",
              "data": "2ke/7+wOQ6OoFd3ZTEFfE28jmucx8Ur5+hz0ACAQndc="
            }
          },
          "drweOSCCe2rhYjQmeEKax87too6GqnI/NwtA8zxncTE=": {
            "valueMac": {
              "type": "Buffer",
              "data": "GMF02401xRDty4o8L2BZS94jUzglyfPEjIB6ops8WA8="
            }
          },
          "aZ9ybEksmUfT8FHqQLq0cLM7Kdl1cMRhDqSE3Ng43AE=": {
            "valueMac": {
              "type": "Buffer",
              "data": "agif1geI6SEv3zJiB8PffXoHi2JravNOtG1bgxhaUuo="
            }
          },
          "UhsPQzgzzC60zPaUi5VEHJk4Qyooc0gua6fBc2PYV7E=": {
            "valueMac": {
              "type": "Buffer",
              "data": "vHg7ilTNOFhf+c1U0XGE4BAm2JUCQdwtjWWZrSEzMuI="
            }
          },
          "r6wpXgFxacfDFcxSXc5RnHUkSLh1pXTdb3cqtL9/D6M=": {
            "valueMac": {
              "type": "Buffer",
              "data": "j9ALhjn9Pe/84clDxLjptj5n/hPuXLOLIdDG/VI3UmM="
            }
          },
          "M7/8Ztt8RJc9yLLK9kEU8sHFobqz9VfHnJ0fPP/gAXE=": {
            "valueMac": {
              "type": "Buffer",
              "data": "+mNfZwUTvtuOK0Vj1Bli7p7lzyaldcQriLXnkXXWQQs="
            }
          },
          "/uKSiInJwbZePLsX26ms7JJZWPtc2Zb+6dyJLj9EDzI=": {
            "valueMac": {
              "type": "Buffer",
              "data": "812DDXKPdMhctNpTkjWLxhgSSGwujEWLmOY2XRiy5t4="
            }
          },
          "9XIsKvmD+ppbLNjF8vJXi882euN5GVM9WSX8ilFbdBI=": {
            "valueMac": {
              "type": "Buffer",
              "data": "nHORHGD9egxOtG36H+wlnSAWdMin3GgUpKdeiKG2AvQ="
            }
          },
          "5VVUGXnIY/IBeDqaAHWNBgX5ENJ4N/O0of7aZp7uLXA=": {
            "valueMac": {
              "type": "Buffer",
              "data": "hNNXNi7nepkeiBlSriONRODX4kRQ5d8qxpT0NY2NJVI="
            }
          },
          "33pZLmeRyOZrp0mRM+IA6t20NxsUNY5lwDUqalB85TM=": {
            "valueMac": {
              "type": "Buffer",
              "data": "fRPj7N5mX/TgV21VHjhf0cNJdEPZ/LtGHQLQKm21AE8="
            }
          },
          "+ldUly5RI+sJCfJEx1GbxwBHKlFVgAIhT51oAOkiCxQ=": {
            "valueMac": {
              "type": "Buffer",
              "data": "t9zHh+AbvWaxBTMpbUzgAvpSFWHJEn0tOP9n0YFD9OA="
            }
          },
          "wFbbpo8Rl1nbnM7qbLhdCZTetd5EsuwXqdZioPjsclw=": {
            "valueMac": {
              "type": "Buffer",
              "data": "EWCAxdWdSIBViqIy6cs/9CVcyB8V+fSTQl75LvnUxrA="
            }
          },
          "DYxcyeLdrnHR+UKtLSRQM9DBQv+YGTq3xqEJr6GLFGQ=": {
            "valueMac": {
              "type": "Buffer",
              "data": "817lMBIjRioOh8ZXTIiJElXBGDMaPb7BbBi3cseelrQ="
            }
          },
          "aN5azt1VES9mBbo7ADT5lTQIy34vBn1oMtDn7TdyKUg=": {
            "valueMac": {
              "type": "Buffer",
              "data": "TGxzpJd7eoY+89hH/Opf6ADY8BIo+82JpXIQFDmf+jE="
            }
          },
          "MtZrzFDQ1HWzFalCCMLym6PV5/6dhq6nQe7pr6yKFW4=": {
            "valueMac": {
              "type": "Buffer",
              "data": "DguSybJkaRmqnKT0oT1LDnVqGHWFpC7c1mjXobrAaYY="
            }
          },
          "Gyy++Ojpj6YzhULT0SrSqUCj5B33t0b0j9Wn+/4elP0=": {
            "valueMac": {
              "type": "Buffer",
              "data": "gUWyDVm7VhSM+cLO1+m6MTr23kTFSRU/gzKwp9gNQlo="
            }
          },
          "MA4ejBUcKqU6hP7WVRM69buG+0DCuyFZ3IJXC0lIybo=": {
            "valueMac": {
              "type": "Buffer",
              "data": "JyzEMmlYED/3RTYakLuTOSmpHo3MkgyOe0NcYcfNG6A="
            }
          },
          "MtOIbQz4ASi0DWkWFMp1YlV4xaPNUyEyPC6aa2HA8g4=": {
            "valueMac": {
              "type": "Buffer",
              "data": "7zA87Gaq4ezeBcx0wkcezjOnhVhQdkqIldm1gRfwDT8="
            }
          },
          "/UiwpEKScbj+tnYToBZqX3A/Hxputz2DJYKDDcU7PMw=": {
            "valueMac": {
              "type": "Buffer",
              "data": "x3dKwfiudvB3iK0dmeEQOn6EkO3n0nh3BF6dX68t48g="
            }
          },
          "s40JmIgAld9nidEa7pugMRd9qk9DxuyPHhwqkSWx1jU=": {
            "valueMac": {
              "type": "Buffer",
              "data": "diLwoQsTOR4F3WIWOu+tD+bDP0cznnBgqixmR442inI="
            }
          },
          "dQowcFAlk3fYfuLFVhkTxVjpi9+5OQKnlUj7Xg+iroU=": {
            "valueMac": {
              "type": "Buffer",
              "data": "pvuxB68NR0lD0oWO09/on2rzwoC4WaHXhKaZ/aIfK+k="
            }
          },
          "H4zyuVjz4YLXFjJFSOw+aL4xp+UbNdToxuab/OAbNVs=": {
            "valueMac": {
              "type": "Buffer",
              "data": "OjHj6PrLO4KWmH/89zqYHy/Uj5b4/btpbsEUh4cc6x0="
            }
          },
          "WIUc9CHiQGRW4zkv+wqwyFPOl+6QjsBXBC1yqDeWV4w=": {
            "valueMac": {
              "type": "Buffer",
              "data": "n6tZk04BEE41uJQzCjhmHNCCYQr2k5xYRenWB47jf68="
            }
          },
          "oRGX3gWBFDAtyFi3GmnZLJvWbTv2re2Sby/Qqu202F8=": {
            "valueMac": {
              "type": "Buffer",
              "data": "hzA5rwmOfWlQMBMJuSEEcKppSKYcTn+BFMSXcpRLmPs="
            }
          },
          "2IQLSPQWfp42Y0FJYhx4NZoGYKAoIez7zqK49UGd3U4=": {
            "valueMac": {
              "type": "Buffer",
              "data": "gKQ5LUtgVtDwHADul1fVkguK7h3lcEM5Z+Zl733ZmgM="
            }
          },
          "BiytoJ9KPcNMx0FIgyfrLuCyCNi15MLfkA4Ypg0M3sU=": {
            "valueMac": {
              "type": "Buffer",
              "data": "0BHhNLXK3/e1aBxs7qse/rmehjmXS2EmFuXD9hoD+zc="
            }
          },
          "lA3TUpuhNIznc59SPvAEqvF1Dg2BL683JywyU1OpSIc=": {
            "valueMac": {
              "type": "Buffer",
              "data": "dUD3VgzdBfuwI5oRX34gbznpCv9dgkNqCv1bdeWZheU="
            }
          },
          "Au3MFy7YqwAWwvgioQlHM371hwerGWE7r61v63huulo=": {
            "valueMac": {
              "type": "Buffer",
              "data": "EZ1J1ffzm+Lpni3IeGzK1XTASRATQ35kLN2gUXuC7o4="
            }
          },
          "0zBfJIarn6+EAP5RqPaGX+jOvT27CcLQhWJN9eNEC3g=": {
            "valueMac": {
              "type": "Buffer",
              "data": "Kv8GbrbZXhP6HmjlM3GhkA7PMfKFH4vqlfPeEyF5630="
            }
          },
          "uNxA2l63uCQ4/r8PZsLqJW3z4OZpdkYhiEAB3czwpkc=": {
            "valueMac": {
              "type": "Buffer",
              "data": "P8wAoBzWeUTLLbLKwEnaFy9BljJxku7so/+y1w2tqoo="
            }
          },
          "3yWwdeglJ8yeCc4t/B1HJUDVYVZAGyZoesdcqGZwBLA=": {
            "valueMac": {
              "type": "Buffer",
              "data": "kcpdXJjaTPHUztHIkVB16JdXrchVaa+xmk6pIlrCzc0="
            }
          },
          "CRkFQ3X66g6N/Q7RpxXvs5oKIarCbeHPl5AJ845PNOs=": {
            "valueMac": {
              "type": "Buffer",
              "data": "mkg3uyDJ9jfeXShpQHyHlJ3Kn2TQtK/ubgKgo0OlyXU="
            }
          },
          "TUceNntNycM3TtjaWPNiXSpmhUJrOHUTSDGbIEQkZhM=": {
            "valueMac": {
              "type": "Buffer",
              "data": "ixrkB5xhS80xGtnrUdRjNJsyP/A0emk+Z3041mKe58M="
            }
          },
          "HdANeYVV/nUnFo/hBKRyatd5nlr5wn0Gmp9vqR6KEhk=": {
            "valueMac": {
              "type": "Buffer",
              "data": "DpjQOjEIPPMW5fMgCuU9DRR5aLrexyjmOYyGn3ubWKA="
            }
          },
          "qeTPDAmp6gxB+gIODGWkJOr0RAGV848/dPY6UJ+Pf/I=": {
            "valueMac": {
              "type": "Buffer",
              "data": "sh+qd5vJWqFjByZU6gJgOaW3wZHw2wmNZHLO3p/leNY="
            }
          },
          "2c+ra0IPiBWXN4WDGvtD/8xN+KVdCcOoq1it+NmI1nA=": {
            "valueMac": {
              "type": "Buffer",
              "data": "kqz9nnb+XdR/68nkoqkAolgOS/4342X++gfIV1KzYdg="
            }
          },
          "x1pBbWq64PY567YOrJqrrE1/BMoW484rLru2GaBqQ68=": {
            "valueMac": {
              "type": "Buffer",
              "data": "8/4vrIZiktt1TAkZ9JnWBT+1IuqELRzm5gAc2d2I4Jw="
            }
          },
          "Uq7sa+4soOYWfRDrRzEnS4uFcEIqNVmYltADc1U4GoI=": {
            "valueMac": {
              "type": "Buffer",
              "data": "bHmQl2b1/5C4VCGawgXXOG34Go04yFzjk3unhuJmFwM="
            }
          },
          "GdPh578yWPCeImWEUqmzVwBwc0IicmpN4L2FtPL12Tw=": {
            "valueMac": {
              "type": "Buffer",
              "data": "RnvMjbXPZdUpYgCKqoBCRjFFvXtbSbh/yqTaJ09zRuk="
            }
          },
          "2457mItFoV6iQ8tFCB6pVBFpMkTqPFEOzM4iixk1Tis=": {
            "valueMac": {
              "type": "Buffer",
              "data": "vpDFxu6EuiLSMSVEYkXOkzSepq8Uac91wME3s4Bwde8="
            }
          },
          "CYG9UZpxUULm8DWXCHMmqdB1+z+ohL9EWsT/zgY3Rus=": {
            "valueMac": {
              "type": "Buffer",
              "data": "Dv7ub5UbF9WciOtml9PwTmcHWAWMa/U+zL8Ft0/0A9s="
            }
          },
          "v2OC8na3D94ut+P7t6MaRHsP9FgsRX5nvBH2snOrA6o=": {
            "valueMac": {
              "type": "Buffer",
              "data": "7IV7bPTiE4IoIhQUmPdE7ySvVoiNzmsCfCiiEZB+fxQ="
            }
          },
          "wQJMJIljjjv+PjuVJ7OpibQ2Lai7P5a4Vmn6QvsuQtc=": {
            "valueMac": {
              "type": "Buffer",
              "data": "ZFztd65mCl/QwAJbua9KCTv4r7IVFkNResnbfHS3fP0="
            }
          },
          "RuTfQwErZRVHCdqjZwSJEN3euQZupXCQaqYdb/9NZ4M=": {
            "valueMac": {
              "type": "Buffer",
              "data": "1gUVFSmJTjvIzXYObFd0t7xCUBxGINp8lSIxOMJqdSU="
            }
          },
          "2MJaAv8TpKcGbwilEbkhclwLIkHZytApl9nlAwG2mGU=": {
            "valueMac": {
              "type": "Buffer",
              "data": "FadUQR41lD2SWrVUr0ZUkjiYHmBlaJa5Bh0mDX7Xg7E="
            }
          },
          "Vw5z9xmiAzpWx53kjAqpx9HNTbnVeaSsS6+kPEUW2kc=": {
            "valueMac": {
              "type": "Buffer",
              "data": "DMIo5+HalDQ73+byZHrKQvtH1lTf9hV6UBuRVAusUX8="
            }
          },
          "DTXhpz2ArNXe256xoWeu1pQwiNV6Qr/pBPspHmRCwlc=": {
            "valueMac": {
              "type": "Buffer",
              "data": "+M9zxbpzeFJXuazds5210JsJI1UOzYBKaU3Gt7x6upQ="
            }
          },
          "o8B1oID/CHwTDR/MhDKkMVHc5Wt3xpcIWBuZcYq0grw=": {
            "valueMac": {
              "type": "Buffer",
              "data": "foWcoE8daHZnRO3P71yyst6LqqjvP/VAKSdhgFEGRCk="
            }
          },
          "3wavznHocUMviTR5n8i4E4qkqko30lccP3b6HdR5Wgg=": {
            "valueMac": {
              "type": "Buffer",
              "data": "M0CrLb2e5k5eDZ6j2t8ybqMeg/MTJcHwVhOSqWInPkI="
            }
          },
          "NK5MOIiciPzeyjvwsaS1OOllapjTIIvPS2p3Gv0iWcQ=": {
            "valueMac": {
              "type": "Buffer",
              "data": "cD8QLaib182lDAmpgtGKAq8LbJH1PCSehaFEkrR9/ik="
            }
          },
          "+/WnuIVCE0uzHdTVJHAKjfm+hhNqWEFSETyhUJNx0yU=": {
            "valueMac": {
              "type": "Buffer",
              "data": "1VOxt6NhUXmi35+3+HsdUlRRPsTDU94AIu2m/2Kguj0="
            }
          },
          "4G2G38ocmQRXQUGHGD4/jmKDCGAdwtOYiv9bWcUEqeM=": {
            "valueMac": {
              "type": "Buffer",
              "data": "zTh985NFGXmaNMdZNiVMEgaDw0MkkLjoJrXgCgAXxI4="
            }
          },
          "hpVu6gtsmafZeqo2IIu1QL+qG5dghEO+vwjqJaO7QBs=": {
            "valueMac": {
              "type": "Buffer",
              "data": "etJtuh27y2sAIJxk/sia4blIc8xD6KGq7ULVBvnyA0U="
            }
          },
          "fm6exKEdN+MAMqzc0XjG5+YiJ3dGdPX4hIYioJ89B9w=": {
            "valueMac": {
              "type": "Buffer",
              "data": "u0WB1aeQ7EuxcHflR12P+Cdu11NCC+oinEJFQtNgL/w="
            }
          },
          "nqHkVOB3auUlF5lKgZljOAiq4uWFdypYRw+cns/BgFs=": {
            "valueMac": {
              "type": "Buffer",
              "data": "L93T2ajSwtfpvlcXXx2RDV6auAj9yGpdjAV25jV6Vbg="
            }
          },
          "ST5F1RUKpuH3nw2XJ1uMP+3lFHkCDKPqCfmTawPhXrE=": {
            "valueMac": {
              "type": "Buffer",
              "data": "eSYsH2ZqjtSv8NCisiITJavdfO+yg/FyQCjJOP5mkqA="
            }
          },
          "VrEb6nhXZQS2ETUM2cZ0tLaNC2wlu1eRlYnkvTPKgU8=": {
            "valueMac": {
              "type": "Buffer",
              "data": "SwpnhVSgO35T5gB8KumzA5t0jHA8GwBe2wmAH5axsBw="
            }
          },
          "NAWwAYMfeWDxfk75LG9iFDgbklzYOQLFGDaofdJhiSg=": {
            "valueMac": {
              "type": "Buffer",
              "data": "OsIBlZYpSAPBhgD0EYEP4f1MphSK4+Yx/6kxl2y/KnY="
            }
          },
          "vLSGZT86Fn59Mq7TK/eZyoizNink4m/+7I/Gy5HBjyI=": {
            "valueMac": {
              "type": "Buffer",
              "data": "v+7V7O49b2BgTI2BZPKmdxkgGaO+Po9tkacoNXL7Z3A="
            }
          },
          "kPF9Ogl9lsDuEN7rTsuTmgZsoOYqJDRzLP2PF8drZhc=": {
            "valueMac": {
              "type": "Buffer",
              "data": "kJmAhQKDxXvtehWkI0uwPshxUYluNt9pHG+MRWFTlYU="
            }
          },
          "WyUJwXOBefItBGXtB4r8MVeymtt6hRCkDaYIzPrlGgU=": {
            "valueMac": {
              "type": "Buffer",
              "data": "zuKy9LmINiXmRoxzucdtX0JLziTVfE9/m9MPGHnEd/I="
            }
          },
          "TpYV9WXmaqGjKPFfazvl0PlFiyCKTwHCaqzg1t2iusw=": {
            "valueMac": {
              "type": "Buffer",
              "data": "PBbvgE13lprxLK9Puf3LSx7OkKjtqJdXseWGCcy76HY="
            }
          },
          "Y/ViwFFg500XAhFyVqbkgwvwjkpIQQru2cfTS9gkNHY=": {
            "valueMac": {
              "type": "Buffer",
              "data": "50Nei1IB7pemoEvl/2IP/8Gym0QtOKgWXFr5Tj3yykM="
            }
          },
          "aON0XzsA8VtPNHbYjYBuIA7dJ8NKOapHuVd2R+87ESc=": {
            "valueMac": {
              "type": "Buffer",
              "data": "/Vgt0NN2wXHI5dGCuGXfOPhnv+S7FHChhNncstLER7c="
            }
          },
          "+glPO9E2EOVYj8JTeMZyApr67h7MyckyYDoM+tX7g7U=": {
            "valueMac": {
              "type": "Buffer",
              "data": "capjDTEsxglYWHe7lRxJ3Ed+u8KYZoY/1aVt5oLKINs="
            }
          },
          "7mNeh2kM9qX71pZq9OOeiNZ+V0eitOhANu3BbGGtAoI=": {
            "valueMac": {
              "type": "Buffer",
              "data": "8fA+Mnmfr3n34xvoXv4phIqMwgCerKQCaF+uBtvVQqc="
            }
          },
          "lXl7m+upnaskYHbujU4vJsxT5QGJhxuzhIiKkhmZsiI=": {
            "valueMac": {
              "type": "Buffer",
              "data": "GDPdbv6bO8kYOwXZobZqfTXgXrygn4uFUqmRDiSwoiQ="
            }
          },
          "qQcUf6ZNfFKi8Ku8aL6xcEkUVZg9WkGwRlB4Fc+evRg=": {
            "valueMac": {
              "type": "Buffer",
              "data": "Yly9PL9jc/ieyPnZnRf8FYNgmdkgSWnHSBxXdLgo1bE="
            }
          },
          "CU4BKVa/pX8vNwQgHqD9i+S0g4fDKXK7VF1j330Fr/k=": {
            "valueMac": {
              "type": "Buffer",
              "data": "PCHDBOpO35TZ47PriXfkM3St8BK6Z6uGFEOU6U/pDB8="
            }
          },
          "a9p+f/k4f7TxBHl5h8RWA4+cxkH6E9z/y+Q2WBSoreA=": {
            "valueMac": {
              "type": "Buffer",
              "data": "jfnRYJKPH20Bh4tI9SqQpfOT1uLX4wbS8cZf8D852zE="
            }
          },
          "W9JmGZQeWCwheJ2Idejs2CQ4MzwCM9SK5f0GLHMN+OE=": {
            "valueMac": {
              "type": "Buffer",
              "data": "vpcJ4+W2NMxlaqazksyFnqkq5A0t5lCaWPwAk5RQZQg="
            }
          },
          "SMghv5yNHG3mRCPCPEQe9wx6Rgq4r4vkIna/3MYLpJ4=": {
            "valueMac": {
              "type": "Buffer",
              "data": "z2fQwKwfxpuVRfi+KdJ6OAkr39fAj0yIkSR5+L70wps="
            }
          },
          "Jlz5d1Kwkz104IiEl+tVNjyhqta0OtWP6bVuEcnDbLc=": {
            "valueMac": {
              "type": "Buffer",
              "data": "5E406G3fwib60Ymut3TkwgPCRhkc3unmY8MgHh6SIXQ="
            }
          },
          "d1u36z5w8kD9aG81L9PwqnbqClIk2qdQHo4P/4uyPnE=": {
            "valueMac": {
              "type": "Buffer",
              "data": "ZX/TUDdl2rDOKnsZfGkBAiUaWOomTIEtpaQMStwfvj4="
            }
          },
          "Eb5POT1efOlxdsgb0FkQZNBsrQvh3GTjfZWcmFaWSmo=": {
            "valueMac": {
              "type": "Buffer",
              "data": "sPndq1FGVwixoQqqm8/2fEGIBUYeRmX4xLU+/s6D/5k="
            }
          },
          "3DaaGbewIQx3hu9YMInmwMf1269Jgpy6uGFT2wYkYFQ=": {
            "valueMac": {
              "type": "Buffer",
              "data": "I2SJwGbZEtOtCMo99wLPw/GOAbmv5Tn1RzZ4918j2Bs="
            }
          },
          "Jh6TtqhHifqtNgSxNiR+RepJAj0VlcV1K9IjLYCr6pg=": {
            "valueMac": {
              "type": "Buffer",
              "data": "/SbkJgPFmHiR7U3nGrhoxSKAVmmE7y8b5lSEbD7nyQs="
            }
          },
          "xwgFOiFv67/zWMQ+YmxW1qv91ebp65vjieQkA40VK2w=": {
            "valueMac": {
              "type": "Buffer",
              "data": "L+NRpcfGGV/DIcznsiOfBUzaa7JopwtPA7c4+xjyoZY="
            }
          },
          "+bveCluwoL+rT1NLEdCLz0Keg+aJ7XhllhnZftnBdLg=": {
            "valueMac": {
              "type": "Buffer",
              "data": "EMUAVO6PWdj+1fZgBe9YvqDPuTar4/ZvIuqgJ4fbamU="
            }
          },
          "D3waI3kncPCZB/8LCOvwHGx3CnhpHArp2EUuabLul48=": {
            "valueMac": {
              "type": "Buffer",
              "data": "tjdCdPwHkLnzjGs8FtDe590PdbJryI5Cp+2bkjioWY8="
            }
          },
          "WScS7/avga4M/k/Ucjn6AJz8hQTpZWNIuacuAYBFNbs=": {
            "valueMac": {
              "type": "Buffer",
              "data": "uBKkldW779qOimYcapVkHmrTLTVZ8Xc1VStsFF9SpZI="
            }
          },
          "Yx/kxfO2JOPO7jbexoCxQMOAE1p8O1m1ruMpSdKpWmE=": {
            "valueMac": {
              "type": "Buffer",
              "data": "sMkDhwJoEMIjYHUTszKXh6ddaQLKFntTHPq6XNvUCOA="
            }
          },
          "K99p3PJIr+xZERn5LpvJv8DTbpeuakpxzaAbagt7UkM=": {
            "valueMac": {
              "type": "Buffer",
              "data": "DL8NukIq2ym66uaMw28KqzMiVkoLKFAHaFAkHvf6tfg="
            }
          },
          "UKPRoVCYZVlJTTfnRyEbyJdE6HOF+LVpPmGxVNgLgk4=": {
            "valueMac": {
              "type": "Buffer",
              "data": "vn5+ax20LiPboA4MjFUaiF0G7e2s6IEvN55hDFzRiG8="
            }
          },
          "zK5NX+Oh8YffZPaH8A2+QwnkAUNZzXW1v1mMfySFxcc=": {
            "valueMac": {
              "type": "Buffer",
              "data": "e3FLy6dNlZvFaNxV6gG1a4Oe9KjwsxWj8rCuHDo+8Ls="
            }
          },
          "40MQrMq7OIZYaWzcSTXcEHnFRFhSmIajS2HQJvBA6ZY=": {
            "valueMac": {
              "type": "Buffer",
              "data": "tkMv/XqXsawhFlUjdWfa0Tr/I7fdQLsRP1BhGArOdiI="
            }
          },
          "YIJl1VQ1mOCSU2PKASEqzU9v1RCGnw75N3NA5BtaOac=": {
            "valueMac": {
              "type": "Buffer",
              "data": "O8tc87AAaNxZ4pgw/yVMVCdHTLe81yCG6PWekaZeAjE="
            }
          },
          "3uAH7aRu2QiUegAzv1lmOPD4nV/4Ie+uZKDX4WAeNII=": {
            "valueMac": {
              "type": "Buffer",
              "data": "jdf0BvkL3/gb5x0gKIVm7zLBWrVYioKGxkaf4iljhjI="
            }
          }
        }
      },
      "regular": {
        "version": 1,
        "hash": {
          "type": "Buffer",
          "data": "1MA5BRQQ+KrnHfwnTCdbWzGGDUAncWTBw72v82bXKUiGs4F6freqPz5bn1YUT2efyaqem/CtAMLhTy0Yu2RnUk7d+ZtLEyJjNF6Pb5MMlswJIBDoHOqFW9wJICmi0FMJwDTj42PzA8aUfKzcOD9wQsFn4DNTsM+XHtFCBElDBWc="
        },
        "indexValueMap": {
          "72bbB1MAamjSZXKsybeMJWwgIGAi3u7mT9TN27465JI=": {
            "valueMac": {
              "type": "Buffer",
              "data": "CkpkgZIZRtdW/H7QFebgmMzPoJnuvwiHVJbueC+T9SA="
            }
          },
          "kWLIlNKYpGd6UYDRUetpxO7cXMW32bs6tqXdUaKs5no=": {
            "valueMac": {
              "type": "Buffer",
              "data": "KfoQsWPjBgzYIJYr4ydIcSq5EvQQWVhcAHe9LBqNFCU="
            }
          },
          "gJnepiEnX7tN4gBZ/lZkvdNrNsNO8HA77WHrB+064fU=": {
            "valueMac": {
              "type": "Buffer",
              "data": "1R6OuUEj3CazLBmyBvnrlQK8tHUQBa5p1rdVuS9YZ0M="
            }
          },
          "l5533aboXQ44QanI1eAdsmbW7aYtixo+iAGyJSkE43M=": {
            "valueMac": {
              "type": "Buffer",
              "data": "mQQDckwbYd40J+cLA0A3Nhp5WmPvnrHry+v6ZV0ctPI="
            }
          },
          "pEH0fd0SPloNTJXE28+itCcMJfWffDzhHbnQ4h8ROnc=": {
            "valueMac": {
              "type": "Buffer",
              "data": "zWVs1mO3345HFzQaHVQRN2af5+TxiZhLP3E4mtNK8BY="
            }
          },
          "v2MUuksFyhEZxhFG+KO2D8Q7Oe4Ddnjy2m2dNrdxKVY=": {
            "valueMac": {
              "type": "Buffer",
              "data": "mLpzswnRs/82/vhtjgV7fNsur8BGcJd4ity1BXA7IxE="
            }
          },
          "hmcsfLRkEGdGDfDbGqIJZanwi6d8VYS6nkAoD73Qihg=": {
            "valueMac": {
              "type": "Buffer",
              "data": "JH2nqJtQrlIEP+WDJC11I+0sTnpn3g02k1IL6cJnz0w="
            }
          }
        }
      },
      "regular_low": {
        "version": 1,
        "hash": {
          "type": "Buffer",
          "data": "v1m7Yb09Nh6P80WJXevVfVJamLtbswmXeu2MAcdCtb6Lm0ZRJU7XuDxjDE9EbQeGX27CwTplaFPurLSoTt5QkJIQ++NN6j/3x9ru1EfeemYE5GSXUOBhmqibujaAXgEpHEhfBkGwBHSz63FKwd3v4i1YpsppDOxNN+UQ+j4y5oE="
        },
        "indexValueMap": {
          "zTW9Muv9gMtgXOcO2riT5tc4pVgbCIK9xdOaeG4Lni0=": {
            "valueMac": {
              "type": "Buffer",
              "data": "1oGVNSs9VIHAXCoD9CDWJxi4ItHn35zpPQgXXdLHUmk="
            }
          },
          "iLqRxCA+krVk7T6OPl6dSk+B8O+FN6KCSNk9uNbkn3s=": {
            "valueMac": {
              "type": "Buffer",
              "data": "vB3TOj45GnZOJ+eQSkM9FpQSa7OGAeRe5aNFesOHG6M="
            }
          },
          "LtHzSw5Q7qYi5XUly+kkxCm7r5oJVYLSQRNiyN1tT7M=": {
            "valueMac": {
              "type": "Buffer",
              "data": "xTYYFJNdlO2UeZXkGDCszXOujLz0NjEMS2B6oZKY7mk="
            }
          },
          "eodQQMBwYz5NHfj12zehLgHpuvvMpdeZ2RVMN1Hy1uw=": {
            "valueMac": {
              "type": "Buffer",
              "data": "LbBTx8oOjOUZnYuWnpOx9K4nGwYz+bL5bfMhQ/hXaYo="
            }
          },
          "1s8UKdEV/849uDwQWtppBSgx/MLkqOt4rcQFyORoXPo=": {
            "valueMac": {
              "type": "Buffer",
              "data": "wElidgB0QKhPZm2i3aZdop9LOrPlAfI27hunyCwI37A="
            }
          },
          "mw1Z6Y/BrI/VOZzsE4nKCVt3j4yvB9VII4e7v/3yQBg=": {
            "valueMac": {
              "type": "Buffer",
              "data": "X6Tgzy/FRojly3Fa7KrT1RH6QD6h+s2PYRINwVme6DE="
            }
          },
          "Eiv1QoFzeGxfgzsIDYS9aiHdJdEQUUCpo6kRtVPz1pU=": {
            "valueMac": {
              "type": "Buffer",
              "data": "h9XnPSxZvu5EgtMOJLHpBxmUTSbVDdJh0R/RAm7aFjk="
            }
          },
          "bKNO7hd+4fdDQm03BcIbQogYFgLiVlegBZf9A3tfGRg=": {
            "valueMac": {
              "type": "Buffer",
              "data": "zKap453T19coS/74HHfWJwSgdA5AQ6SxljEUZSU031s="
            }
          },
          "OCSCnSGxyY2UR+X/9WtHOYlsb5So9Hg9SePxvfh8SMY=": {
            "valueMac": {
              "type": "Buffer",
              "data": "8EedwI6Kd2ri+gr0UzkW7H51qjonG+oEa/0E4I62kYo="
            }
          }
        }
      }
    }
  }
}